{
    "CodeSha256": "1kdN8Sp0K8Kf2L00Ok14yEwyqeT/fjZLjW6z4vwEFpo=", 
    "FunctionName": "hello-world-alexa-skill", 
    "CodeSize": 4650507, 
    "MemorySize": 128, 
    "FunctionArn": "arn:aws:lambda:us-east-1:851751148026:function:hello-world-alexa-skill", 
    "Version": "$LATEST", 
    "Role": "arn:aws:iam::851751148026:role/lambda_basic_execution", 
    "Timeout": 30, 
    "LastModified": "2017-08-15T21:59:37.491+0000", 
    "Handler": "index.handler", 
    "Runtime": "nodejs6.10", 
    "Description": ""
}
